llama_metasearch/__init__.py
llama_metasearch/config.py
llama_metasearch/core.py
llama_metasearch/metasearch.py
llama_metasearch-0.1.0.dist-info/METADATA
llama_metasearch-0.1.0.dist-info/WHEEL
llama_metasearch-0.1.0.dist-info/licenses/LICENSE
llama_metasearch-0.1.0.dist-info/RECORD
