Metadata-Version: 2.4
Name: llama-metasearch
Version: 0.1.0
Summary: Metasearch engine aggregating and ranking results from multiple LlamaAI sources.
Project-URL: Homepage, https://github.com/yourusername/llama-metasearch
Project-URL: Bug Tracker, https://github.com/yourusername/llama-metasearch/issues
Project-URL: Documentation, https://yourusername.github.io/llama-metasearch/
Author-email: Your Name <your.email@example.com>
License: MIT License
License-File: LICENSE
Classifier: Development Status :: 3 - Alpha
Classifier: Intended Audience :: Developers
Classifier: License :: OSI Approved :: MIT License
Classifier: Programming Language :: Python :: 3
Classifier: Programming Language :: Python :: 3.8
Classifier: Programming Language :: Python :: 3.9
Classifier: Programming Language :: Python :: 3.10
Classifier: Programming Language :: Python :: 3.11
Classifier: Topic :: Internet :: WWW/HTTP :: Indexing/Search
Classifier: Topic :: Scientific/Engineering :: Artificial Intelligence
Classifier: Topic :: Software Development :: Libraries :: Python Modules
Requires-Python: >=3.8
Requires-Dist: asyncio>=3.4
Requires-Dist: httpx>=0.24.0
Requires-Dist: llamafind>=0.1.0
Requires-Dist: loguru>=0.7.0
Requires-Dist: numpy>=1.21.0
Requires-Dist: pydantic>=1.10.0
Requires-Dist: scikit-learn>=1.1.0
Provides-Extra: all
Requires-Dist: black>=23.3.0; extra == 'all'
Requires-Dist: fastapi>=0.95.0; extra == 'all'
Requires-Dist: httpx; extra == 'all'
Requires-Dist: isort>=5.12.0; extra == 'all'
Requires-Dist: mkdocs-material>=9.1.6; extra == 'all'
Requires-Dist: mkdocs>=1.4.2; extra == 'all'
Requires-Dist: mkdocstrings[python]>=0.20.0; extra == 'all'
Requires-Dist: mypy>=1.2.0; extra == 'all'
Requires-Dist: pre-commit>=3.3.1; extra == 'all'
Requires-Dist: pytest-asyncio; extra == 'all'
Requires-Dist: pytest-cov>=4.1.0; extra == 'all'
Requires-Dist: pytest-mock>=3.10.0; extra == 'all'
Requires-Dist: pytest>=7.3.1; extra == 'all'
Requires-Dist: ruff>=0.0.260; extra == 'all'
Requires-Dist: uvicorn[standard]>=0.21.0; extra == 'all'
Provides-Extra: api
Requires-Dist: fastapi>=0.95.0; extra == 'api'
Requires-Dist: uvicorn[standard]>=0.21.0; extra == 'api'
Provides-Extra: dev
Requires-Dist: black>=23.3.0; extra == 'dev'
Requires-Dist: httpx; extra == 'dev'
Requires-Dist: isort>=5.12.0; extra == 'dev'
Requires-Dist: mypy>=1.2.0; extra == 'dev'
Requires-Dist: pre-commit>=3.3.1; extra == 'dev'
Requires-Dist: pytest-asyncio; extra == 'dev'
Requires-Dist: pytest-cov>=4.1.0; extra == 'dev'
Requires-Dist: pytest-mock>=3.10.0; extra == 'dev'
Requires-Dist: pytest>=7.3.1; extra == 'dev'
Requires-Dist: ruff>=0.0.260; extra == 'dev'
Provides-Extra: docs
Requires-Dist: mkdocs-material>=9.1.6; extra == 'docs'
Requires-Dist: mkdocs>=1.4.2; extra == 'docs'
Requires-Dist: mkdocstrings[python]>=0.20.0; extra == 'docs'
